{"mode":"playing","coordinateSystem":"true 3D world: x east/west, y altitude, z north/south; player flies through fixed Red Square scene","score":0,"kills":0,"distance":108,"health":100,"speed":89,"throttle":0.55,"threat":1,"mouse":{"x":1,"y":0.47,"firing":false,"pointerLocked":true},"player":{"x":18.09,"y":49.31,"z":56.93,"yaw":0.16,"pitch":-0.2,"roll":-1.08,"forward":{"x":-0.16,"y":-0.19,"z":-0.97}},"counts":{"enemies":86,"enemyFighters":10,"allies":14,"bullets":16,"enemyShots":20,"particles":23},"visibleAirEnemies":[{"hp":4,"x":66.7,"y":56.3,"z":-8,"cooldown":0.4},{"hp":4,"x":-40.8,"y":100.1,"z":-32.3,"cooldown":0.57},{"hp":2,"x":55.4,"y":56.4,"z":-28.6,"cooldown":0.66},{"hp":4,"x":-46.5,"y":80.5,"z":-106,"cooldown":0.58},{"hp":4,"x":72.7,"y":92.4,"z":-181.6,"cooldown":1.28},{"hp":4,"x":-84.3,"y":85.2,"z":-225.8,"cooldown":1.08}],"visibleEnemies":[{"kind":"tank","hp":3,"x":108.4,"y":0.6,"z":64},{"kind":"tank","hp":3,"x":-93.1,"y":0.6,"z":71.7},{"kind":"tank","hp":3,"x":40.1,"y":0.6,"z":-2.6},{"kind":"tank","hp":3,"x":-76.7,"y":0.6,"z":8.6},{"kind":"tank","hp":3,"x":101.2,"y":0.6,"z":-51.7},{"kind":"tank","hp":3,"x":-38.8,"y":0.6,"z":-65.5},{"kind":"tank","hp":3,"x":96.3,"y":0.6,"z":-127.5},{"kind":"tank","hp":3,"x":-42.9,"y":0.6,"z":-121.9}]}